apollox/__init__.py
apollox/__version__.py
apollox/api.py
apollox/error.py
apollox/lib/__init__.py
apollox/lib/enums.py
apollox/lib/utils.py
apollox/rest_api/__init__.py
apollox/rest_api/account.py
apollox/rest_api/data_stream_listen_key.py
apollox/rest_api/market.py
apollox/websocket/__init__.py
apollox/websocket/apollox_client_factory.py
apollox/websocket/apollox_client_protocol.py
apollox/websocket/apollox_socket_manager.py
apollox/websocket/websocket_client.py
apollox/websocket/client/__init__.py
apollox/websocket/client/stream.py
apollox_connector_python1.2-1.2.0.dist-info/LICENSE
apollox_connector_python1.2-1.2.0.dist-info/METADATA
apollox_connector_python1.2-1.2.0.dist-info/WHEEL
apollox_connector_python1.2-1.2.0.dist-info/top_level.txt
apollox_connector_python1.2-1.2.0.dist-info/RECORD
